Metadata-Version: 2.1
Name: fry
Version: 0.1.4
Summary: Library for maintaining tracked requests sessions
Home-page: UNKNOWN
Author: Paul Henke
Author-email: paul.henke@hulu.com
License: Apache 2.0
Keywords: requests stats
Platform: UNKNOWN
Classifier: Development Status :: 3 - Alpha
Classifier: Intended Audience :: Developers
Classifier: Programming Language :: Python :: 2
Classifier: Programming Language :: Python :: 2.7
Classifier: Programming Language :: Python :: 3
Classifier: Programming Language :: Python :: 3.6
Classifier: License :: OSI Approved :: Apache Software License
